arrowetc/__init__.py
arrowetc/arrowetc.py
arrowetc-0.1.12.dist-info/licenses/LICENSE
arrowetc-0.1.12.dist-info/METADATA
arrowetc-0.1.12.dist-info/WHEEL
arrowetc-0.1.12.dist-info/top_level.txt
arrowetc-0.1.12.dist-info/RECORD
