Metadata-Version: 2.4
Name: ArrowETC
Version: 0.1.12
Summary: DEPRECATED: Use ArrowETC via LogicTreeETC instead. https://github.com/carret1268/LogicTreeETC
Author-email: "E. Tyler Carr" <carret1268@gmail.com>
License: CC0 1.0 Universal (CC0 1.0) Public Domain Dedication
Project-URL: Homepage, https://github.com/carret/ArrowETC
Classifier: Development Status :: 7 - Inactive
Classifier: Intended Audience :: Developers
Classifier: Programming Language :: Python :: 3
Classifier: License :: OSI Approved :: MIT License
Classifier: Topic :: Scientific/Engineering :: Visualization
Requires-Python: >=3.10
License-File: LICENSE
Requires-Dist: numpy
Requires-Dist: matplotlib
Requires-Dist: scipy
Dynamic: license-file
